{
  "exams": [
    {
      "subject": "Analysis",
      "name": "ANL1",
      "questions": [
        {
          "nbr": 1,
          "question": "Solve the following integral: ∫(2x^3 - 5x^2 + 3x - 7) dx.",
          "options": [
            "2x^2 - 5x + C",
            "x^3 - 5x^2 + 3x + C",
            "x^4/2 - 5x^3/3 + 3x^2/2 - 7x + C",
            "x^4 + 5x^2 + C"
          ],
          "correct_answer": "x^4/2 - 5x^3/3 + 3x^2/2 - 7x + C",
          "correct_letter": "c",
          "points": 1,
          "type": "easy",
          "hint": "test hint"
        },
        {
          "nbr": 2,
          "question": "Calculate the limit of the function f(x) = (3x^2 - 2x + 1)/(x^2 - 4) as x approaches 2.",
          "options": ["1/4", "2", "∞", "3/2"],
          "correct_answer": "3/2",
          "correct_letter": "d",
          "points": 1,
          "type": "easy",
          "hint": "no-hint"
        },
        {
          "nbr": 3,
          "question": "Study the differentiability of the function f(x) = |x^2 - 4| at x = 2.",
          "options": [
            "Differentiable",
            "Not differentiable",
            "Differentiable only on the right",
            "Differentiable only on the left"
          ],
          "correct_answer": "Not differentiable",
          "correct_letter": "b",
          "points": 2,
          "type": "medium",
          "hint": "no-hint"
        },
        {
          "nbr": 4,
          "question": "Solve the differential equation: y'' + 4y = 0.",
          "options": [
            "y = C1 cos(2x) + C2 sin(2x)",
            "y = C1 e^2x + C2 e^-2x",
            "y = C1 sin(4x) + C2 cos(4x)",
            "y = C1 + C2x"
          ],
          "correct_answer": "y = C1 cos(2x) + C2 sin(2x)",
          "correct_letter": "a",
          "points": 2,
          "type": "medium",
          "hint": "no-hint"
        },
        {
          "nbr": 5,
          "question": "Find the radius of convergence of the series ∑ (x^n / n^2).",
          "options": ["∞", "1", "0", "1/2"],
          "correct_answer": "1",
          "correct_letter": "b",
          "points": 2,
          "type": "medium",
          "hint": "no-hint"
        },
        {
          "nbr": 6,
          "question": "Calculate the Laplace transform of f(t) = t^2 e^(-3t).",
          "options": ["t^2 + 3t", "1/(s+2)^2", "6/(s+3)^4", "2/(s+3)^3"],
          "correct_answer": "2/(s+3)^3",
          "correct_letter": "d",
          "points": 2,
          "type": "medium",
          "hint": "no-hint"
        },
        {
          "nbr": 7,
          "question": "Solve the system of differential equations: dx/dt = 3x + y, dy/dt = -x + 4y.",
          "options": [
            "Oscillatory solutions",
            "Exponential solutions",
            "Logarithmic solutions",
            "Parabolic solutions"
          ],
          "correct_answer": "Exponential solutions",
          "correct_letter": "b",
          "points": 2,
          "type": "medium",
          "hint": "no-hint"
        },
        {
          "nbr": 8,
          "question": "Study the continuity of the function f(x) = 1/(x-3) at x = 3.",
          "options": [
            "Continuous",
            "Discontinuous",
            "Undefined",
            "Right-continuous only"
          ],
          "correct_answer": "Undefined",
          "correct_letter": "c",
          "points": 2,
          "type": "medium",
          "hint": "no-hint"
        },
        {
          "nbr": 9,
          "question": "Solve the improper integral ∫(1/x) dx from 1 to ∞.",
          "options": ["∞", "0", "1", "-∞"],
          "correct_answer": "∞",
          "correct_letter": "a",
          "points": 3,
          "type": "difficult",
          "hint": "no-hint"
        },
        {
          "nbr": 10,
          "question": "Solve the heat equation: u_t = k u_xx.",
          "options": [
            "Logarithmic solution",
            "Exponential solution",
            "Fourier solution",
            "Polynomial solution"
          ],
          "correct_answer": "Fourier solution",
          "correct_letter": "c",
          "points": 3,
          "type": "difficult",
          "hint": "no-hint"
        },
        {
          "nbr": 11,
          "question": "Solve the heat equation: u_t = k u_xx.",
          "options": [
            "Fourier solution",
            "Exponential solution",
            "Logarithmic solution",
            "Polynomial solution"
          ],
          "correct_letter": "a",
          "correct_answer": "Fourier solution",
          "points": 3,
          "type": "difficult",
          "hint": "no-hint"
        },
        {
          "nbr": 12,
          "question": "What is the limit of the function f(x) = 1/x as x approaches 0 from the left?",
          "options": [
            "0",
            "+∞",
            "-∞",
            "The limit does not exist"
          ],
          "correct_letter": "c",
          "correct_answer": "-∞",
          "points": 3,
          "type": "difficult",
          "hint": "no-hint"
        },
        {
          "nbr": 13,
          "question": "A function f(x) is continuous at a point x = a if:",
          "options": [
            "lim(x → a+) f(x) = lim(x → a-) f(x) = f(a)",
            "f(a) exists",
            "The function is differentiable at a",
            "f(a) = 0"
          ],
          "correct_letter": "a",
          "correct_answer": "lim(x → a+) f(x) = lim(x → a-) f(x) = f(a)",
          "points": 3,
          "type": "difficult",
          "hint": "no-hint"
        },
        {
          "nbr": 14,
          "question": "The derivative of the function f(x) = x^3 - 3x^2 + 2x is:",
          "options": [
            "3x^2 - 6x + 2",
            "3x^2 - 6x",
            "x^2 - 3x + 2",
            "x^3 - 2x^2 + 1"
          ],
          "correct_letter": "a",
          "correct_answer": "3x^2 - 6x + 2" ,
          "points": 3,
          "type": "difficult",
          "hint": "no-hint"
        },
        {
          "nbr": 15,
          "question": "What is the primitive of the function f(x) = 2x?",
          "options": [
            "x^2 + C",
            "2x + C",
            "2x^2 + C",
            "x^3 + C"
          ],
          "correct_letter": "a",
          "correct_answer": "x^2 + C" ,
          "points": 3,
          "type": "difficult",
          "hint": "no-hint"
        },
        {
          "nbr": 16,
          "question": "The function f(x) = sin(x) is:",
          "options": [
            "Continuous everywhere but not differentiable",
            "Differentiable but not continuous",
            "Differentiable and continuous everywhere",
            "Neither continuous nor differentiable"
          ],
          "correct_letter": "c",
          "correct_answer": "Differentiable and continuous everywhere",
          "points": 3,
          "type": "difficult",
          "hint": "no-hint"
        },
        {
          "nbr": 17,
          "question": "The calculation of lim(x → ∞) (1/x) gives:",
          "options": [
            "0",
            "+∞",
            "-∞",
            "1"
          ],
          "correct_letter": "a",
          "correct_answer": "0",
          "points": 1,
          "type": "easy",
          "hint": "no-hint"
        },
        {
          "nbr": 18,
          "question": "If f(x) = x^2, what is the domain of differentiability of f(x)?",
          "options": [
            "R (the real numbers)",
            "R\\{0} (the real numbers except 0)",
            "[-∞, 0]",
            "The function is not differentiable"
          ],
          "correct_letter": "a",
          "correct_answer": "R (the real numbers)",
          "points": 3,
          "type": "difficult",
          "hint": "no-hint"
        },
        {
          "nbr": 19,
          "question": "What is the derivative of f(x) = e^x?",
          "options": [
            "e^x",
            "x*e^x",
            "x^2",
            "e^(x+1)"
          ],
          "correct_letter": "a",
          "correct_answer": "e^x",
          "points": 3,
          "type": "difficult",
          "hint": "no-hint"
        },
        {
          "nbr": 20,
          "question": "If f'(x) = 0 for all x in an interval, then:",
          "options": [
            "f(x) is constant",
            "f(x) is linear",
            "f(x) is exponential",
            "f(x) is polynomial"
          ],
          "correct_letter": "a",
          "correct_answer": "f(x) is constant",
          "points": 3,
          "type": "difficult",
          "hint": "no-hint"
        }
      ]
    },
    {
      "subject": "Algebra",
      "name": "ALG1",
      "questions": [
        {
          "nbr": 1,
          "question": "Find the eigenvalues of the matrix A = [[2, -1], [-1, 2]].",
          "options": ["2 and 4", "1 and 3", "0 and 3", "1 and 2"],
          "correct_answer": "1 and 3",
          "correct_letter": "b",
          "points": 1,
          "type": "easy",
          "hint": "no-hint"
        },
        {
          "nbr": 2,
          "question": "Solve the system of linear equations: 3x + 2y = 5 and 2x - y = 3.",
          "options": [
            "x = 1, y = 1",
            "x = 2, y = 1",
            "x = -1, y = 2",
            "x = 0, y = 1"
          ],
          "correct_answer": "x = 1, y = 1",
          "correct_letter": "a",
          "points": 1,
          "type": "easy",
          "hint": "no-hint"
        },
        {
          "nbr": 3,
          "question": "Calculate the determinant of the matrix A = [[1, 2], [3, 4]].",
          "options": ["2", "1", "0", "-2"],
          "correct_answer": "-2",
          "correct_letter": "d",
          "points": 2,
          "type": "medium",
          "hint": "no-hint"
        },
        {
          "nbr": 4,
          "question": "Verify if the vector v = [1, 1] is in the space spanned by the vectors u = [1, 0] and w = [0, 1].",
          "options": ["Yes", "No", "Unknown", "Depends on the scalar"],
          "correct_answer": "Yes",
          "correct_letter": "a",
          "points": 1,
          "type": "easy",
          "hint": "no-hint"
        },
        {
          "nbr": 5,
          "question": "Calculate the norm of the vector u = [3, 4].",
          "options": ["3", "7", "5", "4"],
          "correct_answer": "5",
          "correct_letter": "c",
          "points": 2,
          "type": "medium",
          "hint": "no-hint"
        },
        {
          "nbr": 6,
          "question": "Find the dot product of the vectors u = [1, 2] and v = [2, 3].",
          "options": ["8", "7", "6", "5"],
          "correct_answer": "8",
          "correct_letter": "a",
          "points": 2,
          "type": "medium",
          "hint": "no-hint"
        },
        {
          "nbr": 7,
          "question": "Calculate the rank of the matrix A = [[1, 2, 3], [4, 5, 6], [7, 8, 9]].",
          "options": ["3", "2", "1", "0"],
          "correct_answer": "2",
          "correct_letter": "b",
          "points": 2,
          "type": "medium",
          "hint": "no-hint"
        },
        {
          "nbr": 8,
          "question": "Solve the characteristic equation of the matrix A = [[2, 1], [1, 2]].",
          "options": [
            "λ^2 - 2λ + 1 = 0",
            "λ^2 - 4λ + 3 = 0",
            "λ^2 - 5λ + 6 = 0",
            "λ^2 - 3λ + 2 = 0"
          ],
          "correct_answer": "λ^2 - 3λ + 2 = 0",
          "correct_letter": "d",
          "points": 2,
          "type": "medium",
          "hint": "no-hint"
        },
        {
          "nbr": 9,
          "question": "Determine if the matrix A = [[2, 0], [0, 2]] is diagonalizable.",
          "options": ["Yes", "No", "Depends on the eigenvectors", "Unknown"],
          "correct_answer": "Yes",
          "correct_letter": "a",
          "points": 2,
          "type": "medium",
          "hint": "no-hint"
        },
        {
          "nbr": 10,
          "question": "Calculate the matrix product of A = [[1, 2], [3, 4]] and B = [[2, 0], [1, 2]].",
          "options": ["[4, 4]", "[7, 8]", "[8, 8]", "[5, 4]"],
          "correct_answer": ["[4, 4]", "[7, 8]"],
          "correct_letter": "a",
          "points": 3,
          "type": "difficult",
          "hint": "no-hint"
        },
        {
          "nbr": 11,
          "question": "Find the eigenvectors of the matrix A = [[3, 1], [0, 3]].",
          "options": ["[1, 0]", "[0, 1]", "[1, 1]", "[3, 1]"],
          "correct_answer": "[1, 0]",
          "correct_letter": "a",
          "points": 3,
          "type": "difficult",
          "hint": "no-hint"
        },
        {
          "nbr": 12,
          "question": "Le système d'équations suivant a une solution unique si et seulement si : (2x + 3y = 5, 4x + 6y = 10)",
          "options": [
            "Le déterminant est nul",
            "Les droites sont parallèles",
            "Les droites se coupent en un seul point",
            "Il n'existe pas de solution"
          ],
          "correct_letter": "c",
          "correct_answer": "Les droites se coupent en un seul point",
          "points": 3,
          "type": "difficult",
          "hint": "no-hint"
        },
        {
          "nbr": 13,
          "question": "Si A est une matrice 2x2, alors le déterminant de A est nul si :",
          "options": [
            "A est inversible",
            "Les colonnes de A sont linéairement indépendantes",
            "Les lignes de A sont linéairement dépendantes",
            "Le rang de A est maximal"
          ],
          "correct_letter": "c",
          "correct_answer": "Les lignes de A sont linéairement dépendantes",
          "points": 3,
          "type": "difficult",
          "hint": "no-hint"
        },
        {
          "nbr": 14,
          "question": "Le produit de deux matrices inversibles est :",
          "options": [
            "Toujours inversible",
            "Inversible si et seulement si les matrices sont diagonales",
            "Non inversible",
            "Inversible si les matrices sont carrées"
          ],
          "correct_letter": "a",
          "correct_answer": "Toujours inversible",
          "points": 3,
          "type": "difficult",
          "hint": "no-hint"
        },
        {
          "nbr": 15,
          "question": "Le rang d'une matrice correspond à :",
          "options": [
            "Le nombre de lignes non nulles",
            "Le nombre de colonnes",
            "Le nombre maximal de vecteurs linéairement indépendants",
            "Le nombre de solutions du système associé"
          ],
          "correct_letter": "c",
          "correct_answer": "Le nombre maximal de vecteurs linéairement indépendants",
          "points": 3,
          "type": "difficult",
          "hint": "no-hint"
        },
        {
          "nbr": 16,
          "question": "Le polynôme caractéristique d'une matrice carrée est :",
          "options": [
            "Le déterminant de la matrice",
            "Le polynôme obtenu en prenant le déterminant de (A - λI)",
            "Le produit des valeurs propres de la matrice",
            "Le polynôme dont les racines sont les valeurs propres de A"
          ],
          "correct_letter": "b",
          "correct_answer": "Le polynôme obtenu en prenant le déterminant de (A - λI)",
          "points": 3,
          "type": "difficult",
          "hint": "no-hint"
        },
        {
          "nbr": 17,
          "question": "Une matrice est dite diagonalisable si :",
          "options": [
            "Elle a une base de vecteurs propres",
            "Son déterminant est nul",
            "Elle est inversible",
            "Elle est symétrique"
          ],
          "correct_letter": "a",
          "correct_answer": "Elle a une base de vecteurs propres",
          "points": 3,
          "type": "difficult",
          "hint": "no-hint"
        },
        {
          "nbr": 18,
          "question": "Les valeurs propres d'une matrice sont les racines de :",
          "options": [
            "Le polynôme caractéristique",
            "La matrice inversée",
            "La matrice adjointée",
            "Le déterminant de la matrice"
          ],
          "correct_letter": "a",
          "correct_answer": "Le polynôme caractéristique",
          "points": 3,
          "type": "difficult",
          "hint": "no-hint"
        },
        {
          "nbr": 19,
          "question": "Le déterminant d'une matrice triangulaire est :",
          "options": [
            "La somme des éléments de la diagonale",
            "Le produit des éléments de la diagonale",
            "Toujours nul",
            "Le produit des valeurs propres"
          ],
          "correct_letter": "b",
          "correct_answer": "Le produit des éléments de la diagonale",
          "points": 3,
          "type": "difficult",
          "hint": "no-hint"
          },
        {
          "nbr": 20,
          "question": "Si A est une matrice inversible, alors A^(-1) est :",
          "options": [
            "La matrice obtenue en permutant les lignes et colonnes de A",
            "La transposée de A",
            "La matrice qui, multipliée par A, donne l'identité",
            "Le déterminant de A"
          ],
          "correct_letter": "c",
          "correct_answer": "La matrice qui, multipliée par A, donne l'identité",
          "points": 3,
          "type": "difficult",
          "hint": "no-hint"
        }
      ]
    },
    {
      "subject": "Database",
      "name": "BDD1",
      "questions": [
        {
          "nbr": 1,
          "question": "What is the primary key in a relational database?",
          "options": [
            "A unique attribute",
            "A set of columns",
            "A constraint",
            "An identifier"
          ],
          "correct_answer": "A unique attribute",
          "correct_letter": "a",
          "points": 1,
          "type": "easy",
          "hint": "no-hint"
        },
        {
          "nbr": 2,
          "question": "What is a foreign key in a relational schema?",
          "options": [
            "An attribute linked to the primary key",
            "A constraint",
            "A reference to another table",
            "A type of column"
          ],
          "correct_answer": "A reference to another table",
          "correct_letter": "a",
          "points": 1,
          "type": "easy",
          "hint": "no-hint"
        },
        {
          "nbr": 3,
          "question": "What is the role of the JOIN operation in SQL?",
          "options": [
            "Combine rows from multiple tables",
            "Select columns",
            "Add data",
            "Delete data"
          ],
          "correct_answer": "Combine rows from multiple tables",
          "correct_letter": "a",
          "points": 2,
          "type": "medium",
          "hint": "no-hint"
        },
        {
          "nbr": 4,
          "question": "Which normal form eliminates partial functional dependencies?",
          "options": ["2NF", "3NF", "1NF", "BCNF"],
          "correct_answer": "2NF",
          "correct_letter": "a",
          "points": 2,
          "type": "medium",
          "hint": "no-hint"
        },
        {
          "nbr": 5,
          "question": "What is the SQL statement to delete a table?",
          "options": [
            "DROP TABLE",
            "DELETE TABLE",
            "REMOVE TABLE",
            "ERASE TABLE"
          ],
          "correct_answer": "DROP TABLE",
          "correct_letter": "a",
          "points": 2,
          "type": "medium",
          "hint": "no-hint"
        },
        {
          "nbr": 6,
          "question": "How do you create a new database in SQL?",
          "options": [
            "CREATE DATABASE",
            "NEW DATABASE",
            "MAKE DATABASE",
            "INSERT DATABASE"
          ],
          "correct_answer": "CREATE DATABASE",
          "correct_letter": "a",
          "points": 2,
          "type": "medium",
          "hint": "no-hint"
        },
        {
          "nbr": 7,
          "question": "How do you insert data into an SQL table?",
          "options": ["INSERT INTO", "ADD DATA", "INSERT DATA", "APPEND DATA"],
          "correct_answer": "INSERT INTO",
          "correct_letter": "a",
          "points": 2,
          "type": "medium",
          "hint": "no-hint"
        },
        {
          "nbr": 8,
          "question": "What is the correct syntax to create a foreign key in SQL?",
          "options": [
            "FOREIGN KEY REFERENCES",
            "FOREIGN KEY ->",
            "REFERENCE FOREIGN",
            "LINK FOREIGN"
          ],
          "correct_answer": "FOREIGN KEY REFERENCES",
          "correct_letter": "a",
          "points": 2,
          "type": "medium",
          "hint": "no-hint"
        },
        {
          "nbr": 9,
          "question": "What is a transaction in a database?",
          "options": [
            "A set of operations executed atomically",
            "An update",
            "A data transfer",
            "A data read"
          ],
          "correct_answer": "A set of operations executed atomically",
          "correct_letter": "a",
          "points": 3,
          "type": "difficult",
          "hint": "no-hint"
        },
        {
          "nbr": 10,
          "question": "What is the statement to update data in an SQL table?",
          "options": ["UPDATE", "MODIFY", "CHANGE", "ALTER"],
          "correct_answer": "UPDATE",
          "correct_letter": "a",
          "points": 3,
          "type": "difficult",
          "hint": "no-hint"
        },
        {
          "nbr": 11,
          "question": "Quelle clause SQL est utilisée pour filtrer les résultats d'une requête ?",
          "options": [
            "WHERE",
            "GROUP BY",
            "ORDER BY",
            "HAVING"
          ],
          "correct_letter": "a",
          "correct_answer": "WHERE",
          "points": 3,
          "type": "difficult",
          "hint": "no-hint"
        },
        {
          "nbr": 12,
          "question": "Quelle commande SQL est utilisée pour récupérer des données d'une base de données ?",
          "options": [
            "GET",
            "EXTRACT",
            "SELECT",
            "FETCH"
          ],
          "correct_letter": "c",
          "correct_answer": "SELECT",
          "points": 3,
          "type": "difficult",
          "hint": "no-hint"
        },
        { 
          "nbr": 13,
          "question": "Quelle commande SQL est utilisée pour supprimer des lignes d'une table ?",
          "options": [
            "REMOVE",
            "DROP",
            "DELETE",
            "CLEAR"
          ],
          "correct_letter": "c",
          "correct_answer": "DELETE",
          "points": 3,
          "type": "difficult",
          "hint": "no-hint"
        },
        {
          "nbr": 14,
          "question": "Quelle fonction SQL est utilisée pour compter le nombre de lignes dans un résultat ?",
          "options": [
            "COUNT()",
            "SUM()",
            "TOTAL()",
            "CALCULATE()"
          ],
          "correct_letter": "a",
          "correct_answer": "COUNT()",
          "points": 3,
          "type": "difficult",
          "hint": "no-hint"
        },
        {
          "nbr": 15,
          "question": "Laquelle des commandes suivantes est utilisée pour modifier une table existante en SQL ?",
          "options": [
            "CHANGE TABLE",
            "MODIFY TABLE",
            "ALTER TABLE",
            "UPDATE TABLE"
          ],
          "correct_letter": "c",
          "correct_answer": "ALTER TABLE",
          "points": 3,
          "type": "difficult",
          "hint": "no-hint"
        },
        {
          "nbr": 16,
          "question": "Quelle clause SQL est utilisée pour regrouper les lignes ayant les mêmes valeurs ?",
          "options": [
            "ORDER BY",
            "GROUP BY",
            "PARTITION BY",
            "UNION"
          ],
          "correct_letter": "b",
          "correct_answer": "GROUP BY",
          "points": 3,
          "type": "difficult",
          "hint": "no-hint"
        },
        {
          "nbr": 17,
          "question": "Quelle clause SQL est utilisée pour trier les résultats d'une requête ?",
          "options": [
            "SORT BY",
            "ORDER BY",
            "GROUP BY",
            "ARRANGE BY"
          ],
          "correct_letter": "b",
          "correct_answer": "ORDER BY",
          "points": 3,
          "type": "difficult",
          "hint": "no-hint"
        },
        {
          "nbr": 18,
          "question": "Quelle commande SQL est utilisée pour créer une nouvelle table ?",
          "options": [
            "INSERT INTO",
            "CREATE TABLE",
            "ADD TABLE",
            "NEW TABLE"
          ],
          "correct_letter": "b",
          "correct_answer": "CREATE TABLE",
          "points": 3,
          "type": "difficult",
          "hint": "no-hint"
        },
        {
          "nbr": 19,
          "question": "Quel mot-clé SQL est utilisé pour éliminer les doublons dans les résultats d'une requête ?",
          "options": [
            "DISTINCT",
            "UNIQUE",
            "FILTER",
            "ONLY"
          ],
          "correct_letter": "a",
          "correct_answer": "DISTINCT",
          "points": 3,
          "type": "difficult",
          "hint": "no-hint"
        },
        {
          "nbr": 20,
          "question": "Quelle commande SQL est utilisée pour ajouter de nouvelles données dans une table ?",
          "options": [
            "ADD",
            "APPEND",
            "INSERT INTO",
            "MERGE"
          ],
          "correct_letter": "c",
          "correct_answer": "INSERT INTO",
          "points": 3,
          "type": "difficult",
          "hint": "no-hint"
        }
      ]
    },
    {
      "subject": "OOP",
      "name": "concepts",
      "questions": [
        {
          "nbr": 1,
          "question": "What does OOP stand for?",
          "options": [
            "Object-Oriented Programming",
            "Organized Object Programming",
            "Operation-Oriented Programming",
            "Object-Oriented Process"
          ],
          "correct_answer": "Object-Oriented Programming",
          "correct_letter": "a",
          "points": 1,
          "type": "easy",
          "hint": "no-hint"
        },
        {
          "nbr": 2,
          "question": "What is a class in OOP?",
          "options": [
            " An instance of an object",
            "A blueprint for creating objects",
            "A method that performs an action",
            "A variable that stores data"
          ],
          "correct_answer": "A blueprint for creating objects",
          "correct_letter": "b",
          "points": 1,
          "type": "easy",
          "hint": "no-hint"
        },
        {
          "nbr": 3,
          "question": "What is an object in OOP?",
          "options": [
            " A class definition",
            "An instance of a class",
            "A method that performs an action",
            "A variable that stores data"
          ],
          "correct_answer": "An instance of a class",
          "correct_letter": "b",
          "points": 1,
          "type": "easy",
          "hint": "no-hint"
        },
        {
          "nbr": 4,
          "question": "What is a constructor?",
          "options": [
            " A method used to delete an object",
            "A special method used to initialize objects",
            "A method that returns values",
            "A method used to access private variables"
          ],
          "correct_answer": "A special method used to initialize objects",
          "correct_letter": "b",
          "points": 1,
          "type": "easy",
          "hint": "no-hint"
        },
        {
          "nbr": 5,
          "question": "Which concept allows you to hide implementation details and show only functionality?",
          "options": [
            "  Inheritance",
            "Abstraction",
            "Inheritance",
            "Encapsulation"
          ],
          "correct_answer": "Abstraction",
          "correct_letter": "b",
          "points": 1,
          "type": "easy",
          "hint": "no-hint"
        },
        {
          "nbr": 6,
          "question": " What is a destructor in OOP?",
          "options": [
            "   A function called to initialize an object",
            "A method used for inheritance",
            "A function called to destroy an object",
            "A function for overloading operators"
          ],
          "correct_answer": "A function called to destroy an object",
          "correct_letter": "c",
          "points": 1,
          "type": "easy",
          "hint": "no-hint"
        },
        {
          "nbr": 7,
          "question": " What is function overloading?",
          "options": [
            "Using the same function name with different parameters",
            "Defining multiple classes with the same name",
            "Assigning multiple return types to a single function",
            "Using functions without parameters"
          ],
          "correct_answer": "Using the same function name with different parameters",
          "correct_letter": "a",
          "points": 1,
          "type": "easy",
          "hint": "no-hint"
        },
        {
          "nbr": 8,
          "question": " What is meant by overriding in OOP?",
          "options": [
            " Redefining a base class method in a derived class",
            " Using the same name for multiple functions",
            "Accessing private members of a class",
            "Destroying an object"
          ],
          "correct_answer": "Redefining a base class method in a derived class",
          "correct_letter": "a",
          "points": 1,
          "type": "easy",
          "hint": "no-hint"
        },
        {
          "nbr": 9,
          "question": "Which of the following languages use Object-Oriented Programming?",
          "options": ["C++", " Java", "Python", "All of the above"],
          "correct_answer": "All of the above",
          "correct_letter": "d",
          "points": 1,
          "type": "easy",
          "hint": "no-hint"
        },
        {
          "nbr": 10,
          "question": "Which OOP concept involves creating a new class based on an existing class?",
          "options": [
            " Encapsulation",
            " Abstraction",
            "Inheritance",
            "Polymorphism"
          ],
          "correct_answer": "Inheritance",
          "correct_letter": "c",
          "points": 1,
          "type": "easy",
          "hint": "no-hint"
        },
        {
          "nbr": 11,
          "question": "What is the difference between an interface and an abstract class in OOP?",
          "options": [
            " An interface can have both abstract and concrete methods, while an abstract class can only have abstract methods",
            "  An interface can only have abstract methods, while an abstract class can have both abstract and concrete methods",
            "An interface is used for inheritance, while an abstract class is used for polymorphism",
            " An interface is used for polymorphism, while an abstract class is used for inheritance"
          ],
          "correct_answer": "An interface can only have abstract methods, while an abstract class can have both abstract and concrete methods",
          "correct_letter": "b",
          "points": 2,
          "type": "medium",
          "hint": "no-hint"
        },
        {
          "nbr": 12,
          "question": "How does encapsulation contribute to code security in OOP?",
          "options": [
            "By exposing all data to external access",
            "By hiding data and exposing methods, thus controlling access to data",
            "By creating multiple objects from a single class",
            "By overriding methods in child classes"
          ],
          "correct_answer": "By hiding data and exposing methods, thus controlling access to data",
          "correct_letter": "b",
          "points": 2,
          "type": "medium",
          "hint": "no-hint"
        },
        {
          "nbr": 13,
          "question": "What is the difference between a static method and an instance method in OOP?",
          "options": [
            "A static method belongs to a class and can be called without creating an instance, while an instance method belongs to an object and requires an instance to be called.",
            "A static method belongs to an object and requires an instance to be called, while an instance method belongs to a class and can be called without creating an instance.",
            "A static method is used for hiding data, while an instance method is used for exposing methods.",
            "A static method is used for exposing methods, while an instance method is used for hiding data."
          ],
          "correct_answer": "A static method belongs to a class and can be called without creating an instance, while an instance method belongs to an object and requires an instance to be called.",
          "correct_letter": "a",
          "points": 2,
          "type": "medium",
          "hint": "no-hint"
        },
        {
          "nbr": 14,
          "question": "Which of the following is a correct way to create a class?",
          "options": [
            " class MyClass { } ",
            "object MyClass { }",
            "MyClass() { }",
            " create class MyClass { }"
          ],
          "correct_answer": " class MyClass { } ",
          "correct_letter": "a",
          "points": 2,
          "type": "medium",
          "hint": "no-hint"
        },
        {
          "nbr": 15,
          "question": " What does the 'super' keyword represent in Java?",
          "options": [
            "  Current class ",
            "Parent class",
            "Static method",
            " Final method"
          ],
          "correct_answer": " Parent class ",
          "correct_letter": "b",
          "points": 2,
          "type": "medium",
          "hint": "no-hint"
        },
        {
          "nbr": 16,
          "question": " Which of the following keywords is used to prevent a class from being inherited?",
          "options": ["  virtual ", "final", "const", " static"],
          "correct_answer": " final ",
          "correct_letter": "b",
          "points": 2,
          "type": "medium",
          "hint": "no-hint"
        },
        {
          "nbr": 17,
          "question": "  What happens when a class is declared abstract?",
          "options": [
            "   It cannot have any methods or fields ",
            "Objects of the class cannot be created, but it can be inherited",
            "It must implement all of its methods immediately",
            " It can be used as a standalone class for instantiation"
          ],
          "correct_answer": " Objects of the class cannot be created, but it can be inherited ",
          "correct_letter": "b",
          "points": 2,
          "type": "medium",
          "hint": "no-hint"
        },
        {
          "nbr": 18,
          "question": "  Attributes of an object are also known as",
          "options": ["   methods", " properties", "classes", " functions"],
          "correct_answer": "properties",
          "correct_letter": "b",
          "points": 1,
          "type": "easy",
          "hint": "no-hint"
        },
        {
          "nbr": 19,
          "question": " What does the public access modifier allow in OOP?",
          "options": [
            "   Access only within the same package",
            " Access only within the same class",
            " Access from anywhere outside the class",
            " Access only by subclasses"
          ],
          "correct_answer": "Access from anywhere outside the class",
          "correct_letter": "c",
          "points": 2,
          "type": "medium",
          "hint": "no-hint"
        },
        {
          "nbr": 20,
          "question": "  Converting a primitive type data into its corresponding wrapper class object instance is called",
          "options": ["   Boxing", "Wrapping", "Instantiation", " Autoboxing"],
          "correct_answer": "Autoboxing",
          "correct_letter": "d",
          "points": 2,
          "type": "medium",
          "hint": "no-hint"
        }
      ]
    },
    {
      "subject": "PYTHON",
      "name": "PythonBasics",
      "questions": [
        {
          "nbr": 1,
          "question": "What is the correct way to output 'Hello, World!' in Python?",
          "options": [
            "echo 'Hello, World!'",
            "print('Hello, World!')",
            "console.log('Hello, World!')",
            "System.out.println('Hello, World!')"
          ],
          "correct_answer": "print('Hello, World!')",
          "correct_letter": "b",
          "points": 1,
          "type": "easy",
          "hint": "no-hint"
        },
        {
          "nbr": 2,
          "question": "What is the data type of the value 3.14 in Python?",
          "options": ["int", "float", "str", "bool"],
          "correct_answer": "float",
          "correct_letter": "b",
          "points": 1,
          "type": "easy",
          "hint": "no-hint"
        },
        {
          "nbr": 3,
          "question": "What is the correct way to comment a single line in Python?",
          "options": [
            " // This is a comment",
            " # This is a comment",
            " /* This is a comment */",
            "-- This is a comment"
          ],
          "correct_answer": " # This is a comment",
          "correct_letter": "b",
          "points": 1,
          "type": "easy",
          "hint": "no-hint"
        },
        {
          "nbr": 4,
          "question": "Which of the following is a valid variable name in Python?",
          "options": ["1variable", " global", " my_variable", "variable-1"],
          "correct_answer": "my_variable",
          "correct_letter": "c",
          "points": 1,
          "type": "easy",
          "hint": "no-hint"
        },
        {
          "nbr": 5,
          "question": "How do you swap the values of two variables in Python without using a third variable?",
          "options": [
            "x = y; y = x",
            " x, y = y, x",
            " temp = x; x = y; y = temp",
            "x + y; y = x; x = y"
          ],
          "correct_answer": " x, y = y, x",
          "correct_letter": "b",
          "points": 1,
          "type": "easy",
          "hint": "no-hint"
        },
        {
          "nbr": 6,
          "question": "Which of the following data types is immutable in Python?",
          "options": ["List", " Set", " Dictionary", "Tuple"],
          "correct_answer": "Tuple",
          "correct_letter": "d",
          "points": 1,
          "type": "easy",
          "hint": "no-hint"
        },
        {
          "nbr": 7,
          "question": "What does the type() function return in Python?",
          "options": [
            "The value of the variable",
            " The type of the variable",
            " The memory address of the variable",
            "The length of the variable"
          ],
          "correct_answer": "The type of the variable",
          "correct_letter": "b",
          "points": 1,
          "type": "easy",
          "hint": "no-hint"
        },
        {
          "nbr": 8,
          "question": "Which of the following function convert a string to a float in python?",
          "options": [
            "int(x [,base])",
            " long(x [,base] )",
            " float(x)",
            "str(x)"
          ],
          "correct_answer": "float(x)",
          "correct_letter": "c",
          "points": 1,
          "type": "easy",
          "hint": "no-hint"
        },
        {
          "nbr": 9,
          "question": "What is the output of the expression : 3*1**3",
          "options": ["27", "9", "3", "1"],
          "correct_answer": "3",
          "correct_letter": "c",
          "points": 1,
          "type": "easy",
          "hint": "no-hint"
        },
        {
          "nbr": 10,
          "question": "What is the output of the following code : print(9//2)",
          "options": ["4.5", "4.0", "4", "Error"],
          "correct_answer": "4",
          "correct_letter": "c",
          "points": 1,
          "type": "easy",
          "hint": "no-hint"
        },
        {
          "nbr": 11,
          "question": "Which function overloads the >> operator?",
          "options": ["more()", "gt()", "ge()", "None of the above"],
          "correct_answer": "None of the above",
          "correct_letter": "d",
          "points": 1,
          "type": "easy",
          "hint": "no-hint"
        },
        {
          "nbr": 12,
          "question": "Which operator is overloaded by the or() function?",
          "options": ["||", "|", "//", "/"],
          "correct_answer": "|",
          "correct_letter": "b",
          "points": 1,
          "type": "easy",
          "hint": "no-hint"
        },
        {
          "nbr": 13,
          "question": "What is the purpose of the if statement in Python?",
          "options": [
            "To define a function",
            "To declare a variable",
            "To execute a block of code conditionally",
            "To create a loop"
          ],
          "correct_answer": "To execute a block of code conditionally",
          "correct_letter": "c",
          "points": 1,
          "type": "easy",
          "hint": "no-hint"
        },
        {
          "nbr": 14,
          "question": "Which of the following operators is used for equality comparison in Python?",
          "options": ["==", "=", "!=", ">"],
          "correct_answer": "==",
          "correct_letter": "a",
          "points": 1,
          "type": "easy",
          "hint": "no-hint"
        },
        {
          "nbr": 15,
          "question": "How do you represent the logical AND operator in Python?",
          "options": ["&&", "and", "AND", "&"],
          "correct_answer": "and",
          "correct_letter": "b",
          "points": 1,
          "type": "easy",
          "hint": "no-hint"
        },
        {
          "nbr": 16,
          "question": "Which statement is used to exit a loop prematurely in Python?",
          "options": ["break", "exit", "return", "continue"],
          "correct_answer": "break",
          "correct_letter": "a",
          "points": 1,
          "type": "easy",
          "hint": "no-hint"
        },
        {
          "nbr": 17,
          "question": "Suppose li is [3, 4, 5, 20, 5, 25, 1, 3], what is li after li.pop(1)?",
          "options": [
            "[3, 4, 5, 20, 5, 25, 1, 3]",
            "[1, 3, 3, 4, 5, 5, 20, 25]",
            "[3, 5, 20, 5, 25, 1, 3]",
            "[1, 3, 4, 5, 20, 5, 25]"
          ],
          "correct_answer": "[3, 5, 20, 5, 25, 1, 3]",
          "correct_letter": "c",
          "points": 1,
          "type": "easy",
          "hint": "no-hint"
        },
        {
          "nbr": 18,
          "question": " How can you iterate over the elements of a list in reverse order using a for loop?",
          "options": [
            "Using the reversed function",
            "Using the reverse method",
            "Using a negative step in the range function",
            "Python doesn't support iterating in reverse order"
          ],
          "correct_answer": "Using a negative step in the range function",
          "correct_letter": "c",
          "points": 1,
          "type": "easy",
          "hint": "no-hint"
        },
        {
          "nbr": 19,
          "question": " What is the purpose of the find() function in Python strings?",
          "options": [
            "It returns the position of the last occurrence of a substring within a string",
            "It returns true if the string begins with a specified prefix",
            "It returns the position of the first occurrence of a substring within a string",
            "Python doesn't support iterating in reverse order"
          ],
          "correct_answer": "It returns the position of the first occurrence of a substring within a string",
          "correct_letter": " c",
          "points": 1,
          "type": "easy",
          "hint": "no-hint"
        },
        {
          "nbr": 20,
          "question": " Which method is used to replace all tab characters with whitespace using the given tab size?",
          "options": ["strip()", "expandtabs()", "replace()", "maketrans()"],
          "correct_answer": "expandtabs()",
          "correct_letter": "b",
          "points": 1,
          "type": "easy",
          "hint": "no-hint"
        }
      ]
    },
    {
      "subject": "PYTHON",
      "name": "PythonException",
      "questions": [
        {
          "nbr": 1,
          "question": "What is an exception in Python?",
          "options": [
            "echo 'A syntax error'",
            "A runtime error",
            "A logical error",
            "A compile-time error"
          ],
          "correct_answer": "A runtime error",
          "correct_letter": "b",
          "points": 1,
          "type": "easy",
          "hint": "no-hint"
        },
        {
          "nbr": 2,
          "question": "How can you handle exceptions in Python?",
          "options": ["Using if-else statements",
           "Using try-except blocks",
            "Using switch-case statements",
             "Using for loops"
            ],
          "correct_answer": "Using try-except blocks",
          "correct_letter": "b",
          "points": 1,
          "type": "easy",
          "hint": "no-hint"
        },
        {
          "nbr": 3,
          "question": "What is the purpose of the finally block in exception handling?",
          "options": [
            " To define a block of code that will be executed if an exception occurs",
            "To specify the code to be executed regardless of whether an exception occurs or not",
            " To catch and handle specific exceptions",
            "To raise a custom exception"
          ],
          "correct_answer": "To specify the code to be executed regardless of whether an exception occurs or not",
          "correct_letter": "b",
          "points": 1,
          "type": "easy",
          "hint": "no-hint"
        },
        {
          "nbr": 4,
          "question": "Which of the following statements is used to raise a custom exception in Python?",
          "options": ["throw", " catch", " raise ", "except"],
          "correct_answer": "raise ",
          "correct_letter": "c",
          "points": 1,
          "type": "easy",
          "hint": "no-hint"
        },
        {
          "nbr": 5,
          "question": "What is the purpose of the else block in exception handling?",
          "options": [
            "To handle exceptions",
            "To specify code that will be executed if no exceptions are raised",
            " To define custom exceptions",
            "To skip the execution of the block if an exception occurs"
          ],
          "correct_answer": "To specify code that will be executed if no exceptions are raised",
          "correct_letter": "b",
          "points": 1,
          "type": "easy",
          "hint": "no-hint"
        },
        {
          "nbr": 6,
          "question": "How can you catch multiple exceptions in a single except block?",
          "options": ["Using a comma-separated list of exceptions",
           " Using nested try-except blocks",
            "By defining a custom exception",
             "Using the catch keyword"],
          "correct_answer": "Using a comma-separated list of exceptions",
          "correct_letter": "a",
          "points": 1,
          "type": "easy",
          "hint": "no-hint"
        },
        {
          "nbr": 7,
          "question": "What is the purpose of the assert statement in Python exception handling?",
          "options": [
            "To catch and handle exceptions",
            "To raise a custom exception",
            " To check if a given expression is true, otherwise raise an 'AssertionError'",
            "To ignore exceptions"
          ],
          "correct_answer": "To check if a given expression is true, otherwise raise an 'AssertionError'",
          "correct_letter": "c",
          "points": 1,
          "type": "easy",
          "hint": "no-hint"
        },
        {
          "nbr": 8,
          "question": "What does the finally block execute if an exception is raised and not caught?",
          "options": [
            "It doesn't execute",
            " It executes before the exception is raised",
            " It executes after the exception is raised",
            "It executes only if the exception is caught"
          ],
          "correct_answer": "It executes after the exception is raised",
          "correct_letter": "c",
          "points": 1,
          "type": "easy",
          "hint": "no-hint"
        },
        {
          "nbr": 9,
          "question": "How can you handle exceptions globally in Python?",
          "options": ["Using the `global_exception_handler()` function",
           "By using the `global` keyword",
            "By modifying the global exception settings in the `sys` module",
             "There is no way to handle exceptions globally"],
          "correct_answer": "By modifying the global exception settings in the `sys` module",
          "correct_letter": "c",
          "points": 1,
          "type": "easy",
          "hint": "no-hint"
        },
        {
          "nbr": 10,
          "question": "In Python, what does the sys.exc_info() function return?",
          "options": ["The exception type",
           "The exception value",
            "A tuple containing the exception type, value, and traceback",
             "A dictionary containing exception information"
            ],
          "correct_answer": "A tuple containing the exception type, value, and traceback",
          "correct_letter": "c",
          "points": 1,
          "type": "easy",
          "hint": "no-hint"
        },
        {
          "nbr": 11,
          "question": "What is the purpose of the raise statement in Python?",
          "options": ["To terminate the program",
           "To catch an exception",
            "To ignore an exception",
             "To raise an arbitrary exception"
            ],
          "correct_answer": "To raise an arbitrary exception",
          "correct_letter": "d",
          "points": 1,
          "type": "easy",
          "hint": "no-hint"
        },
        {
          "nbr": 12,
          "question": "Which method is used to replace a pattern in a string using RegEx?",
          "options": ["replace()", "sub()", "re.replace()", "substitute()"],
          "correct_answer": "sub()",
          "correct_letter": "b",
          "points": 1,
          "type": "easy",
          "hint": "no-hint"
        },
        {
          "nbr": 13,
          "question": "Which method is used to check if a pattern is present anywhere in a string using RegEx?",
          "options": [
            "locate()",
            "find()",
            "search()",
            "match()"
          ],
          "correct_answer": "search()",
          "correct_letter": "c",
          "points": 1,
          "type": "easy",
          "hint": "no-hint"
        },
        {
          "nbr": 14,
          "question": "How can you make a RegEx pattern match across multiple lines in Python?",
          "options": ["re.MULTILINE",
           "re.SINGLELINE",
            "re.LINEALL",
             "re.GLOBAL"],
          "correct_answer": "re.MULTILINE",
          "correct_letter": "a",
          "points": 1,
          "type": "easy",
          "hint": "no-hint"
        },
        {
          "nbr": 15,
          "question": "Which Python exception is raised when you try to access an undefined variable?",
          "options": ["NameError", "TypeError", "KeyError", "IndexError"],
          "correct_answer": "NameError",
          "correct_letter": "a",
          "points": 1,
          "type": "easy",
          "hint": "no-hint"
        },
        {
          "nbr": 16,
          "question": "What does the 'with' statement help to simplify in Python?",
          "options": [
            "String concatenation",
            "Error handling",
            "File and resource management",
            "Looping"
          ],
          "correct_answer": "File and resource management",
          "correct_letter": "c",
          "points": 1,
          "type": "easy",
          "hint": "no-hint"
        },
        {
          "nbr": 17,
          "question": "What is the purpose of the 'except Exception as e' syntax in Python?",
          "options": [
            "To re-raise an exception",
            "To handle all exceptions and store the exception details in 'e'",
            "To suppress exceptions",
            "To log exceptions without handling them"
          ],
          "correct_answer": "To handle all exceptions and store the exception details in 'e'",
          "correct_letter": "b",
          "points": 1,
          "type": "easy",
          "hint": "no-hint"
        },
        {
          "nbr": 18,
          "question": "What type of error is raised when you try to divide by zero in Python?",
          "options": [
            "ZeroDivisionError",
            "ValueError",
            "TypeError",
            "IndexError"
          ],
          "correct_answer": "ZeroDivisionError",
          "correct_letter": "a",
          "points": 1,
          "type": "easy",
          "hint": "no-hint"
        },
        {
          "nbr": 19,
          "question": "Which of the following statements is used to catch exceptions in Python?",
          "options": [
            "if",
            "except",
            "for",
            "when"
          ],
          "correct_answer": "except",
          "correct_letter": "b",
          "points": 1,
          "type": "easy",
          "hint": "no-hint"
        },
        {
          "nbr": 20,
          "question": "What is the correct way to raise a custom exception in Python?",
          "options": [
            "throw CustomException()",
            "raise CustomException()",
            "custom_exception()",
            "raise error CustomException()"
          ],
          "correct_answer": "raise CustomException()",
          "correct_letter": "b",
          "points": 1,
          "type": "easy",
          "hint": "no-hint"
        }


      ]
    },
    {
      "subject": "PYTHON",
      "name": "PythonFileHandling",
      "questions": [
        {
          "nbr": 1,
          "question": "What is file handling in Python?",
          "options": [
            "Managing folders",
            "Reading and writing file",
            "Controlling system files",
            "Handling exceptions in files"
          ],
          "correct_answer": "Reading and writing file",
          "correct_letter": "b",
          "points": 1,
          "type": "easy",
          "hint": "no-hint"
        },
        {
          "nbr": 2,
          "question": "Which function is used to open a file in Python?",
          "options": ["open_file()", "read_file()", "file_open()", "open()"],
          "correct_answer": " open()",
          "correct_letter": "d",
          "points": 1,
          "type": "easy",
          "hint": "no-hint"
        },
        {
          "nbr": 3,
          "question": "Which method is used to read the entire content of a file as a string?",
          "options": [" read_all()", "read()", " read_full()", "readfile()"],
          "correct_answer": "read()",
          "correct_letter": "b",
          "points": 1,
          "type": "easy",
          "hint": "no-hint"
        },
        {
          "nbr": 4,
          "question": "What is the purpose of the 'rb' mode in file opening?",
          "options": [
            "Read binary",
            "Replace binary",
            "Read and backup",
            "Rename binary"
          ],
          "correct_answer": "Read binary",
          "correct_letter": "a",
          "points": 1,
          "type": "easy",
          "hint": "no-hint"
        },
        {
          "nbr": 5,
          "question": "What is the purpose of the 'a' mode in file opening?",
          "options": ["Add", " Append", "Access", "Assign"],
          "correct_answer": " Append",
          "correct_letter": "b",
          "points": 1,
          "type": "easy",
          "hint": "no-hint"
        },
        {
          "nbr": 6,
          "question": "How can you read the first five characters of a file in Python?",
          "options": [
            "file.read(5)",
            "read(file, 5)",
            " read_first(file, 5)",
            "file.read_first(5)"
          ],
          "correct_answer": "file.read(5)",
          "correct_letter": "a",
          "points": 1,
          "type": "easy",
          "hint": "no-hint"
        },
        {
          "nbr": 7,
          "question": "How do you check if a file exists before opening it in Python?",
          "options": [
            "check_file_existence()",
            " file_exists()",
            " os.path.exists()",
            "verify_file()"
          ],
          "correct_answer": "os.path.exists()",
          "correct_letter": "c",
          "points": 1,
          "type": "easy",
          "hint": "no-hint"
        },
        {
          "nbr": 8,
          "question": "What is the purpose of the 'with' statement in file handling?",
          "options": [
            "It creates a new file",
            " It automatically closes the file",
            " It appends data to a file",
            "It reads the entire file at once"
          ],
          "correct_answer": "It automatically closes the file",
          "correct_letter": "b",
          "points": 1,
          "type": "easy",
          "hint": "no-hint"
        },
        {
          "nbr": 9,
          "question": "How do you read a file line by line in Python?",
          "options": [
            "read_all_lines()",
            "file.read_line()",
            "readlines()",
            "read_line(file)"
          ],
          "correct_answer": "readlines()",
          "correct_letter": "c",
          "points": 1,
          "type": "easy",
          "hint": "no-hint"
        },
        {
          "nbr": 10,
          "question": "How can you write data to a file without overwriting its existing content in Python?",
          "options": [
            "file.write_data()",
            "write_file()",
            "file.write_append()",
            "file.write('a')"
          ],
          "correct_answer": "file.write_append()",
          "correct_letter": "c",
          "points": 1,
          "type": "easy",
          "hint": "no-hint"
        },
        {
          "nbr": 11,
          "question": "Which function checks if a file exists?",
          "options": [
            "exists_file()",
            "check_file()",
            "os.path.exists()",
            "file_exists()"
          ],
          "correct_answer": "os.path.exists()",
          "correct_letter": "c",
          "points": 1,
          "type": "easy",
          "hint": "no-hint"
        },
        {
          "nbr": 12,
          "question": "How do you check if a file is writable in Python?",
          "options": [
            "file.writable()",
            "os.path.writable()",
            "os.access(file, os.W_OK)",
            "file.is_writable()"
          ],
          "correct_answer": "os.access(file, os.W_OK)",
          "correct_letter": "c",
          "points": 1,
          "type": "easy",
          "hint": "no-hint"
        },
        {
          "nbr": 13,
          "question": "Which method is used to move the cursor to a specific position in a file?",
          "options": [
            "file.seek()",
            "move_cursor()",
            "cursor_position()",
            "set_position()"
          ],
          "correct_answer": "file.seek()",
          "correct_letter": "a",
          "points": 1,
          "type": "easy",
          "hint": "no-hint"
        },
        {
          "nbr": 14,
          "question": "What does the 'a+b' mode stand for in file opening?",
          "options": [
            "Append and Binary",
            "Access and Backup",
            "Append and Backup",
            "Access and Binary"
          ],
          "correct_answer": "Append and Binary",
          "correct_letter": "a",
          "points": 1,
          "type": "easy",
          "hint": "no-hint"
        },
        {
          "nbr": 15,
          "question": "How do you copy the content of one file to another in Python?",
          "options": [
            "copy_file()",
            "file.copy()",
            "shutil.copyfile()",
            "copy_to()"
          ],
          "correct_answer": "shutil.copyfile()",
          "correct_letter": "c",
          "points": 1,
          "type": "easy",
          "hint": "no-hint"
        },
        {
          "nbr": 16,
          "question": "Which method is used to return the current position of the file cursor?",
          "options": [
            "file.position()",
            "get_cursor_position()",
            "file.tell()",
            "cursor_location()"
          ],
          "correct_answer": "file.tell()",
          "correct_letter": "c",
          "points": 1,
          "type": "easy",
          "hint": "no-hint"
        },
        {
          "nbr": 17,
          "question": "Which Python module provides high-level file and directory handling operations?",
          "options": [
            "os",
            "sys",
            "shutil",
            "fileutil"
          ],
          "correct_answer": "shutil",
          "correct_letter": "c",
          "points": 1,
          "type": "easy",
          "hint": "no-hint"
        },
        {
          "nbr": 18,
          "question": "What does the 'w' mode do when opening a file in Python?",
          "options": [
            "Writes to a file and deletes existing content",
            "Writes to a file without deleting content",
            "Appends content to the file",
            "Opens the file in read-only mode"
          ],
          "correct_answer": "Writes to a file and deletes existing content",
          "correct_letter": "a",
          "points": 1,
          "type": "easy",
          "hint": "no-hint"
        },
        {
          "nbr": 19,
          "question": "What is the purpose of the 'encoding' parameter in the open() function?",
          "options": [
            "To specify the file format",
            "To define how the file content is interpreted as text",
            "To enable binary file handling",
            "To set file read/write permissions"
          ],
          "correct_answer": "To define how the file content is interpreted as text",
          "correct_letter": "b",
          "points": 1,
          "type": "easy",
          "hint": "no-hint"
        },
        {
          "nbr": 20,
          "question": "What is the default mode when opening a file using open() in Python?",
          "options": [
            "r",
            "w",
            "rb",
            "a"
          ],
          "correct_answer": "r",
          "correct_letter": "a",
          "points": 1,
          "type": "easy",
          "hint": "no-hint"
        }
      ]
    },
    {
      "subject": "Database",
      "name": "BDDpro",
      "questions": [
        {
          "nbr": 1,
          "question": "What is the purpose of a transaction log in a database?",
          "options": [
            "To store temporary data",
            "To record all changes made to the database",
            "To optimize query performance",
            "To back up the database"
          ],
          "correct_answer": "To record all changes made to the database",
          "correct_letter": "b",
          "points": 2,
          "type": "medium",
          "hint": "no-hint"
        },
        {
          "nbr": 2,
          "question": "Which isolation level ensures that no dirty reads, non-repeatable reads, or phantom reads occur?",
          "options": [
            "Read Uncommitted",
            "Read Committed",
            "Repeatable Read",
            "Serializable"
          ],
          "correct_answer": "Serializable",
          "correct_letter": "d",
          "points": 3,
          "type": "difficult",
          "hint": "no-hint"
        },
        {
          "nbr": 3,
          "question": "What is the purpose of a materialized view in a database?",
          "options": [
            "To store the result of a query for faster access",
            "To create a temporary table",
            "To optimize joins",
            "To enforce constraints"
          ],
          "correct_answer": "To store the result of a query for faster access",
          "correct_letter": "a",
          "points": 2,
          "type": "medium",
          "hint": "no-hint"
        },
        {
          "nbr": 4,
          "question": "Which SQL command is used to grant privileges to a user?",
          "options": [
            "GRANT",
            "ALLOW",
            "PERMIT",
            "AUTHORIZE"
          ],
          "correct_answer": "GRANT",
          "correct_letter": "a",
          "points": 1,
          "type": "easy",
          "hint": "no-hint"
        },
        {
          "nbr": 5,
          "question": "What is the purpose of the CASCADE option in a foreign key constraint?",
          "options": [
            "To automatically delete related rows in child tables",
            "To enforce uniqueness",
            "To optimize query performance",
            "To create a backup"
          ],
          "correct_answer": "To automatically delete related rows in child tables",
          "correct_letter": "a",
          "points": 2,
          "type": "medium",
          "hint": "no-hint"
        }
      ]
    }
  ]
}